CHANGELOG.md
LICENSE
MANIFEST.in
README.md
setup.cfg
setup.py
ffprog/__init__.py
ffprog/exceptions.py
ffprog/main.py
ffprog/readers.py
ffprog.egg-info/PKG-INFO
ffprog.egg-info/SOURCES.txt
ffprog.egg-info/dependency_links.txt
ffprog.egg-info/entry_points.txt
ffprog.egg-info/not-zip-safe
ffprog.egg-info/requires.txt
ffprog.egg-info/top_level.txt
ffprog/async_readers/__init__.py
ffprog/async_readers/readers.py